evonet/__init__.py
evonet/activation.py
evonet/connection.py
evonet/core.py
evonet/core_mit_plot_simple.py
evonet/enums.py
evonet/io.py
evonet/layer.py
evonet/mutation.py
evonet/neuron.py
evonet/serialization.py
evonet/utils.py
evonet/visualize.py
evonet-0.1.0.dev28.dist-info/licenses/LICENSE
evonet-0.1.0.dev28.dist-info/METADATA
evonet-0.1.0.dev28.dist-info/WHEEL
evonet-0.1.0.dev28.dist-info/top_level.txt
evonet-0.1.0.dev28.dist-info/RECORD
