Metadata-Version: 2.4
Name: evonet
Version: 0.1.0.dev28
Summary: Evolvable neural network core for integration with EvoLib
Author-email: EvoLib <evolib@dismail.de>
License: MIT License
Classifier: Development Status :: 3 - Alpha
Classifier: License :: OSI Approved :: MIT License
Classifier: Programming Language :: Python :: 3
Classifier: Programming Language :: Python :: 3.10
Classifier: Programming Language :: Python :: 3.11
Classifier: Topic :: Scientific/Engineering :: Artificial Intelligence
Requires-Python: >=3.10
License-File: LICENSE
Requires-Dist: numpy>=1.24
Requires-Dist: pyyaml>=6.0
Requires-Dist: pandas>=2.3.0
Requires-Dist: pydantic<3.0,>=2.7
Requires-Dist: graphviz>=0.20.1
Requires-Dist: matplotlib
Provides-Extra: dev
Requires-Dist: mypy; extra == "dev"
Requires-Dist: types-PyYAML; extra == "dev"
Provides-Extra: docs
Requires-Dist: sphinx; extra == "docs"
Requires-Dist: sphinx-rtd-theme; extra == "docs"
Requires-Dist: myst-parser; extra == "docs"
Dynamic: license-file
